django_grpc_swagger/__init__.py
django_grpc_swagger/admin.py
django_grpc_swagger/apps.py
django_grpc_swagger/models.py
django_grpc_swagger/serializers.py
django_grpc_swagger/tests.py
django_grpc_swagger/views.py
django_grpc_swagger/management/__init__.py
django_grpc_swagger/management/commands/__init__.py
django_grpc_swagger/management/commands/generate_proto.py
django_grpc_swagger/migrations/__init__.py
django_grpc_swagger-0.1.1.dist-info/METADATA
django_grpc_swagger-0.1.1.dist-info/WHEEL
django_grpc_swagger-0.1.1.dist-info/top_level.txt
django_grpc_swagger-0.1.1.dist-info/RECORD
