Metadata-Version: 2.1
Name: django-grpc-swagger
Version: 0.1.1
Summary: Django with gRPC、Swagger
Home-page: https://github.com/tuweifeng/django_grpc_swagger
Author: tuweifeng
Author-email: 907391489@qq.com
License: MIT
Platform: any
Classifier: Development Status :: 4 - Beta
Classifier: License :: OSI Approved :: MIT License
Classifier: Operating System :: OS Independent
Classifier: Intended Audience :: Developers
Classifier: Programming Language :: Python :: 3 :: Only
Classifier: Programming Language :: Python :: 3.6
Classifier: Programming Language :: Python :: 3.7
Classifier: Programming Language :: Python :: 3.8
Classifier: Programming Language :: Python :: 3.9
Classifier: Programming Language :: Python :: 3.10
Classifier: Topic :: Software Development :: Libraries :: Python Modules
Classifier: Framework :: Django
Classifier: Framework :: Django :: 3.2
Requires-Python: >=3.6
Requires-Dist: django (<=3.2.12,>=3.2.9)
Requires-Dist: drf-yasg (>=1.20.0)
Requires-Dist: grpcio-tools (>=1.44.0)
Requires-Dist: djangogrpcframework (>=0.2.1)
Requires-Dist: djangorestframework (>=3.12.4)
